xgse/__init__.py
xgse/engine/loader.py
xgse/engine/prompts.py
xgse/engine/retrieve.py
xgse/engine/schema.py
xgse/engine/skill_engine.py
xgse/engine/spec.py
xgse/sandbox/e2b_sandbox.py
xgse/sandbox/sandbox_base.py
xgse/sandbox/sandbox_factory.py
xgse/utils/__init__.py
xgse/utils/llm_client.py
xgse/utils/setup_env.py
xgse/utils/utils.py
xgse-0.1.1.dist-info/METADATA
xgse-0.1.1.dist-info/WHEEL
xgse-0.1.1.dist-info/entry_points.txt
xgse-0.1.1.dist-info/RECORD
