Metadata-Version: 2.4
Name: xgse
Version: 0.1.1
Summary: Extreme General Skill Engine
Requires-Python: >=3.11
Requires-Dist: colorlog>=6.9.0
Requires-Dist: e2b-code-interpreter>=2.4.1
Requires-Dist: langfuse==2.60.9
Requires-Dist: litellm>=1.81.0
Provides-Extra: examples
Requires-Dist: langchain-community==0.3.20; extra == 'examples'
Requires-Dist: langgraph==0.6.5; extra == 'examples'
